{
  "type": "Feature",
  "properties": {
    "gn:admin1_code":"00",
    "gn:asciiname":"Namiwawang",
    "gn:country_code":"GF",
    "gn:dem":10,
    "gn:feature_class":"P",
    "gn:feature_code":"PPL",
    "gn:name":"Namiwawang",
    "gn:population":0,
    "gn:timezone":"America/Paramaribo",
    "iso:country":"GF",
    "name:fra_x_preferred":[
        "Namiwawang"
    ],
    "wof:name":"Namiwawang",
    "wof:placetype":"locality"
},
  "geometry": {"coordinates":[-54.43717,5.01743],"type":"Point"}
}