{
  "type": "Feature",
  "properties": {
    "gn:admin1_code":"00",
    "gn:asciiname":"Entoucas",
    "gn:cc2":"GF",
    "gn:country_code":"GF",
    "gn:dem":118,
    "gn:feature_class":"P",
    "gn:feature_code":"PPL",
    "gn:name":"Entoucas",
    "gn:population":0,
    "gn:timezone":"America/Cayenne",
    "iso:country":"GF",
    "name:und_x_variant":[
        "Entouca",
        "Entoucas"
    ],
    "wof:name":"Entoucas",
    "wof:placetype":"locality"
},
  "geometry": {"coordinates":[-54.01667,3.48333],"type":"Point"}
}