{
  "type": "Feature",
  "properties": {
    "iso:country":"GF",
    "name:fra_x_preferred":[
        "Cit\u00e9 C\u00e9saire"
    ],
    "name:fre_x_colloquial":[
        "Cite Cesaire"
    ],
    "qs:gn_adm0_cc":"GF",
    "qs:gn_fcode":"PPLX",
    "qs:gn_local":3382160,
    "qs:gn_namadm1":"00",
    "qs:gn_name":"Cit\u00e9 C\u00e9saire",
    "qs:local_max":808,
    "qs:local_sum":1047,
    "qs:localhoods":3,
    "qs:name":"Cit\u00e9 C\u00e9saire",
    "qs:name_adm0":"Guyane Fran\u00e7aise",
    "qs:name_adm1":"Cayenne",
    "qs:name_adm2":"Cayenne",
    "qs:name_local":"Cayenne",
    "qs:photo_max":537,
    "qs:photo_sum":808,
    "qs:placetype":"Suburb",
    "qs:quad_count":10,
    "qs:woe_adm0":23424811,
    "qs:woe_adm1":2345321,
    "qs:woe_adm2":55998454,
    "qs:woe_lau":0,
    "qs:woe_local":379832,
    "qs:woe_ver":"7.10.0",
    "wof:name":"Cit\u00e9 C\u00e9saire",
    "wof:placetype":"neighbourhood"
},
  "geometry": {"coordinates":[-52.32803,4.939118],"type":"Point"}
}