{
  "type": "Feature",
  "properties": {
    "gn:admin1_code":"GF",
    "gn:admin2_code":"973",
    "gn:admin3_code":"9732",
    "gn:admin4_code":"97353",
    "gn:asciiname":"Village Creole",
    "gn:country_code":"GF",
    "gn:dem":171,
    "gn:feature_class":"P",
    "gn:feature_code":"PPL",
    "gn:name":"Village Cr\u00e9ole",
    "gn:population":0,
    "gn:timezone":"America/Cayenne",
    "iso:country":"GF",
    "name:und_x_variant":[
        "Madame Yeyenne",
        "Village Cr\u00e9ole"
    ],
    "wof:name":"Village Creole",
    "wof:placetype":"locality"
},
  "geometry": {"coordinates":[-53.70628000000001,3.21999],"type":"Point"}
}