{
  "type": "Feature",
  "properties": {
    "gn:admin1_code":"GF",
    "gn:admin2_code":"973",
    "gn:admin3_code":"9732",
    "gn:admin4_code":"97311",
    "gn:asciiname":"Koyona",
    "gn:country_code":"GF",
    "gn:dem":1,
    "gn:feature_class":"P",
    "gn:feature_code":"PPL",
    "gn:name":"Koyona",
    "gn:population":0,
    "gn:timezone":"America/Cayenne",
    "iso:country":"GF",
    "name:fra_x_preferred":[
        "Koyona"
    ],
    "wof:name":"Koyona",
    "wof:placetype":"locality"
},
  "geometry": {"coordinates":[-54.11706,5.39166],"type":"Point"}
}