{
  "type": "Feature",
  "properties": {
    "gn:admin1_code":"GF",
    "gn:admin2_code":"973",
    "gn:admin3_code":"9731",
    "gn:admin4_code":"97307",
    "gn:asciiname":"Cogneau",
    "gn:country_code":"GF",
    "gn:dem":12,
    "gn:feature_class":"P",
    "gn:feature_code":"PPL",
    "gn:name":"Cogneau",
    "gn:population":0,
    "gn:timezone":"America/Cayenne",
    "iso:country":"GF",
    "wof:name":"Cogneau",
    "wof:placetype":"locality"
},
  "geometry": {"coordinates":[-52.3235,4.86989],"type":"Point"}
}