{
  "type": "Feature",
  "properties": {
    "gn:admin1_code":"GF",
    "gn:admin2_code":"973",
    "gn:admin3_code":"9732",
    "gn:admin4_code":"97353",
    "gn:asciiname":"Degrad Nicole",
    "gn:country_code":"GF",
    "gn:dem":235,
    "gn:feature_class":"P",
    "gn:feature_code":"PPL",
    "gn:name":"D\u00e9grad Nicole",
    "gn:population":0,
    "gn:timezone":"America/Cayenne",
    "iso:country":"GF",
    "wof:name":"Degrad Nicole",
    "wof:placetype":"locality"
},
  "geometry": {"coordinates":[-53.75,3.55],"type":"Point"}
}