{
  "type": "Feature",
  "properties": {
    "gn:admin1_code":"00",
    "gn:asciiname":"Doglis",
    "gn:country_code":"GF",
    "gn:dem":108,
    "gn:feature_class":"P",
    "gn:feature_code":"PPL",
    "gn:name":"Doglis",
    "gn:population":0,
    "gn:timezone":"America/Cayenne",
    "iso:country":"GF",
    "name:und_x_variant":[
        "Docris",
        "Doglis"
    ],
    "wof:name":"Doglis",
    "wof:placetype":"locality"
},
  "geometry": {"coordinates":[-54.12548,3.79428],"type":"Point"}
}