{
  "type": "Feature",
  "properties": {
    "gn:admin1_code":"GF",
    "gn:admin2_code":"973",
    "gn:admin3_code":"9731",
    "gn:admin4_code":"97308",
    "gn:asciiname":"Tampak",
    "gn:country_code":"GF",
    "gn:dem":18,
    "gn:feature_class":"P",
    "gn:feature_code":"PPL",
    "gn:name":"Tampak",
    "gn:population":0,
    "gn:timezone":"America/Cayenne",
    "iso:country":"GF",
    "name:und_x_variant":[
        "Tampac",
        "Tampak"
    ],
    "wof:name":"Tampak",
    "wof:placetype":"locality"
},
  "geometry": {"coordinates":[-51.78594,3.94548],"type":"Point"}
}