{
  "type": "Feature",
  "properties": {
    "gn:admin1_code":"GF",
    "gn:admin2_code":"973",
    "gn:admin3_code":"9731",
    "gn:admin4_code":"97356",
    "gn:asciiname":"Camopi",
    "gn:country_code":"GF",
    "gn:dem":92,
    "gn:feature_class":"P",
    "gn:feature_code":"PPL",
    "gn:name":"Camopi",
    "gn:population":0,
    "gn:timezone":"America/Cayenne",
    "iso:country":"GF",
    "wof:name":"Camopi",
    "wof:placetype":"locality"
},
  "geometry": {"coordinates":[-52.46063,3.21147],"type":"Point"}
}