{
  "type": "Feature",
  "properties": {
    "gn:admin1_code":"GF",
    "gn:admin2_code":"973",
    "gn:admin3_code":"9731",
    "gn:admin4_code":"97356",
    "gn:asciiname":"Camopi",
    "gn:country_code":"GF",
    "gn:dem":92,
    "gn:feature_class":"P",
    "gn:feature_code":"PPL",
    "gn:name":"Camopi",
    "gn:population":0,
    "gn:timezone":"America/Cayenne",
    "iso:country":"GF",
    "name:ara_x_preferred":[
        "\u0643\u0627\u0645\u0648\u0628\u064a"
    ],
    "name:cat_x_preferred":[
        "Camopi"
    ],
    "name:ceb_x_preferred":[
        "Camopi"
    ],
    "name:deu_x_preferred":[
        "Camopi"
    ],
    "name:fra_x_preferred":[
        "Camopi"
    ],
    "name:ind_x_preferred":[
        "Camopi"
    ],
    "name:ita_x_preferred":[
        "Camopi"
    ],
    "name:lat_x_preferred":[
        "Camopi"
    ],
    "name:msa_x_preferred":[
        "Camopi"
    ],
    "name:nld_x_preferred":[
        "Camopi"
    ],
    "name:oci_x_preferred":[
        "Camopi"
    ],
    "name:pms_x_preferred":[
        "Camopi"
    ],
    "name:pol_x_preferred":[
        "Camopi"
    ],
    "name:por_x_preferred":[
        "Camopi"
    ],
    "name:rus_x_preferred":[
        "\u041a\u0430\u043c\u043e\u043f\u0438"
    ],
    "name:slk_x_preferred":[
        "Camopi"
    ],
    "name:spa_x_preferred":[
        "Camopi"
    ],
    "name:swe_x_preferred":[
        "Camopi"
    ],
    "name:ukr_x_preferred":[
        "\u041a\u0430\u043c\u043e\u043f\u0456"
    ],
    "name:vie_x_preferred":[
        "Camopi"
    ],
    "name:war_x_preferred":[
        "Camopi"
    ],
    "wof:name":"Camopi",
    "wof:placetype":"locality"
},
  "geometry": {"coordinates":[-52.46063,3.21147],"type":"Point"}
}