{
  "type": "Feature",
  "properties": {
    "gn:admin1_code":"GF",
    "gn:admin2_code":"973",
    "gn:admin3_code":"9732",
    "gn:admin4_code":"97362",
    "gn:asciiname":"L'Enfant Perdu",
    "gn:country_code":"GF",
    "gn:dem":100,
    "gn:feature_class":"P",
    "gn:feature_code":"PPL",
    "gn:name":"L\u2019Enfant Perdu",
    "gn:population":0,
    "gn:timezone":"America/Paramaribo",
    "iso:country":"GF",
    "name:und_x_variant":[
        "Enfants perdus",
        "L\u2019Enfant Perdu"
    ],
    "wof:name":"L'Enfant Perdu",
    "wof:placetype":"locality"
},
  "geometry": {"coordinates":[-54.21564,3.85797],"type":"Point"}
}