{
  "type": "Feature",
  "properties": {
    "gn:admin1_code":"GF",
    "gn:admin2_code":"973",
    "gn:admin3_code":"9732",
    "gn:admin4_code":"97311",
    "gn:asciiname":"Maripa",
    "gn:country_code":"GF",
    "gn:dem":19,
    "gn:feature_class":"P",
    "gn:feature_code":"PPL",
    "gn:name":"Maripa",
    "gn:population":0,
    "gn:timezone":"America/Cayenne",
    "iso:country":"GF",
    "name:fra_x_preferred":[
        "Maripa"
    ],
    "name:fra_x_variant":[
        "F\u00e9no"
    ],
    "name:nld_x_preferred":[
        "Maripa"
    ],
    "name:ron_x_preferred":[
        "Maripa"
    ],
    "name:swe_x_preferred":[
        "Maripa"
    ],
    "wof:name":"Maripa",
    "wof:placetype":"locality"
},
  "geometry": {"coordinates":[-54.19608,5.30245],"type":"Point"}
}