{
  "type": "Feature",
  "properties": {
    "gn:admin1_code":"GF",
    "gn:admin2_code":"973",
    "gn:admin3_code":"9731",
    "gn:admin4_code":"97313",
    "gn:asciiname":"Tonnegrande",
    "gn:country_code":"GF",
    "gn:dem":7,
    "gn:feature_class":"P",
    "gn:feature_code":"PPL",
    "gn:name":"Tonn\u00e9grande",
    "gn:population":0,
    "gn:timezone":"America/Cayenne",
    "iso:country":"GF",
    "name:und_x_variant":[
        "Tonnigrande",
        "Ton\u00e9grande",
        "Tonn\u00e9grande"
    ],
    "wof:name":"Tonnegrande",
    "wof:placetype":"locality"
},
  "geometry": {"coordinates":[-52.44378,4.82962],"type":"Point"}
}