{
  "type": "Feature",
  "properties": {
    "gn:admin1_code":"GF",
    "gn:admin2_code":"973",
    "gn:admin3_code":"9732",
    "gn:admin4_code":"97353",
    "gn:asciiname":"Tampok",
    "gn:country_code":"GF",
    "gn:dem":116,
    "gn:feature_class":"P",
    "gn:feature_code":"PPL",
    "gn:name":"Tampok",
    "gn:population":0,
    "gn:timezone":"America/Cayenne",
    "iso:country":"GF",
    "name:fra_x_preferred":[
        "Tampok"
    ],
    "name:pol_x_preferred":[
        "Tampoc"
    ],
    "wof:name":"Tampok",
    "wof:placetype":"locality"
},
  "geometry": {"coordinates":[-53.83532,3.32363],"type":"Point"}
}