{
  "type": "Feature",
  "properties": {
    "gn:admin1_code":"GF",
    "gn:admin2_code":"973",
    "gn:admin3_code":"9731",
    "gn:admin4_code":"97358",
    "gn:asciiname":"Saint-Eugene",
    "gn:country_code":"GF",
    "gn:dem":40,
    "gn:feature_class":"P",
    "gn:feature_code":"PPL",
    "gn:name":"Saint-Eug\u00e8ne",
    "gn:population":0,
    "gn:timezone":"America/Cayenne",
    "iso:country":"GF",
    "name:fra_x_preferred":[
        "Saint-Eug\u00e8ne"
    ],
    "wof:name":"Saint-Eugene",
    "wof:placetype":"locality"
},
  "geometry": {"coordinates":[-53.07321999999999,4.84897],"type":"Point"}
}