{
  "type": "Feature",
  "properties": {
    "gn:admin1_code":"GF",
    "gn:admin2_code":"973",
    "gn:admin3_code":"9731",
    "gn:admin4_code":"97310",
    "gn:asciiname":"Changement",
    "gn:country_code":"GF",
    "gn:dem":66,
    "gn:feature_class":"P",
    "gn:feature_code":"PPL",
    "gn:name":"Changement",
    "gn:population":0,
    "gn:timezone":"America/Cayenne",
    "iso:country":"GF",
    "wof:name":"Changement",
    "wof:placetype":"locality"
},
  "geometry": {"coordinates":[-52.41667,4.48333],"type":"Point"}
}