{
  "type": "Feature",
  "properties": {
    "gn:country":"GF",
    "gn:fcode":"ADM4",
    "gn:population":3605,
    "iso:country":"GF",
    "name:eng_x_preferred":[
        "Saint-Georges"
    ],
    "name:fra_x_preferred":[
        "Saint-Georges"
    ],
    "qs_pg:aaroncc":"GF",
    "qs_pg:gn_country":"GF",
    "qs_pg:gn_fcode":"ADM4",
    "qs_pg:gn_pop":3605,
    "qs_pg:name":"Saint-Georges-de-l'Oyapock",
    "qs_pg:photos_9r":0,
    "qs_pg:photos_sr":0,
    "qs_pg:pop_sr":4,
    "qs_pg:qs_pg_placetype":"localadmin",
    "wof:name":"Saint-Georges-de-l'Oyapock",
    "wof:placetype":"localadmin",
    "wof:population":3605
},
  "geometry": {"coordinates":[-51.8011,3.8894],"type":"Point"}
}