{
  "type": "Feature",
  "properties": {
    "gn:admin1_code":"GF",
    "gn:admin2_code":"973",
    "gn:admin3_code":"9732",
    "gn:admin4_code":"97353",
    "gn:asciiname":"Tolinga",
    "gn:country_code":"GF",
    "gn:dem":118,
    "gn:feature_class":"P",
    "gn:feature_code":"PPL",
    "gn:name":"Tolinga",
    "gn:population":0,
    "gn:timezone":"America/Cayenne",
    "iso:country":"GF",
    "name:fra_x_preferred":[
        "Tolinga"
    ],
    "wof:name":"Tolinga",
    "wof:placetype":"locality"
},
  "geometry": {"coordinates":[-53.9309,3.66463],"type":"Point"}
}