{
  "type": "Feature",
  "properties": {
    "gn:admin1_code":"GF",
    "gn:admin2_code":"973",
    "gn:admin3_code":"9731",
    "gn:admin4_code":"97301",
    "gn:asciiname":"Florissante",
    "gn:country_code":"GF",
    "gn:dem":153,
    "gn:feature_class":"P",
    "gn:feature_code":"PPL",
    "gn:name":"Florissante",
    "gn:population":0,
    "gn:timezone":"America/Cayenne",
    "iso:country":"GF",
    "wof:name":"Florissante",
    "wof:placetype":"locality"
},
  "geometry": {"coordinates":[-52.8991,3.39059],"type":"Point"}
}