{
  "type": "Feature",
  "properties": {
    "gn:admin1_code":"GF",
    "gn:admin2_code":"973",
    "gn:admin3_code":"9732",
    "gn:admin4_code":"97361",
    "gn:asciiname":"Coswine",
    "gn:country_code":"GF",
    "gn:dem":31,
    "gn:feature_class":"P",
    "gn:feature_code":"PPL",
    "gn:name":"Coswine",
    "gn:population":0,
    "gn:timezone":"America/Cayenne",
    "iso:country":"GF",
    "name:und_x_variant":[
        "Camp de Coswine",
        "Coswine"
    ],
    "wof:name":"Coswine",
    "wof:placetype":"locality"
},
  "geometry": {"coordinates":[-53.94993,5.67092],"type":"Point"}
}