{
  "type": "Feature",
  "properties": {
    "gn:admin1_code":"GF",
    "gn:admin2_code":"973",
    "gn:admin3_code":"9732",
    "gn:admin4_code":"97362",
    "gn:asciiname":"Tcha Tcha",
    "gn:country_code":"GF",
    "gn:dem":89,
    "gn:feature_class":"P",
    "gn:feature_code":"PPL",
    "gn:name":"Tcha Tcha",
    "gn:population":0,
    "gn:timezone":"America/Cayenne",
    "iso:country":"GF",
    "name:fra_x_preferred":[
        "Tcha Tcha"
    ],
    "wof:name":"Tcha Tcha",
    "wof:placetype":"locality"
},
  "geometry": {"coordinates":[-54.25064,3.90568],"type":"Point"}
}