{
  "type": "Feature",
  "properties": {
    "gn:admin1_code":"GF",
    "gn:admin2_code":"973",
    "gn:admin3_code":"9732",
    "gn:admin4_code":"97357",
    "gn:asciiname":"Grand Bala",
    "gn:country_code":"GF",
    "gn:dem":62,
    "gn:feature_class":"P",
    "gn:feature_code":"PPL",
    "gn:name":"Grand Bala",
    "gn:population":0,
    "gn:timezone":"America/Cayenne",
    "iso:country":"GF",
    "wof:name":"Grand Bala",
    "wof:placetype":"locality"
},
  "geometry": {"coordinates":[-54.30337,4.393],"type":"Point"}
}