{
  "type": "Feature",
  "properties": {
    "gn:admin1_code":"GF",
    "gn:admin2_code":"973",
    "gn:admin3_code":"9731",
    "gn:admin4_code":"97358",
    "gn:asciiname":"Embouchure",
    "gn:country_code":"GF",
    "gn:dem":33,
    "gn:feature_class":"P",
    "gn:feature_code":"PPL",
    "gn:name":"Embouchure",
    "gn:population":0,
    "gn:timezone":"America/Cayenne",
    "iso:country":"GF",
    "name:fra_x_preferred":[
        "Embouchure"
    ],
    "wof:name":"Embouchure",
    "wof:placetype":"locality"
},
  "geometry": {"coordinates":[-53.03229,4.974],"type":"Point"}
}