{
  "type": "Feature",
  "properties": {
    "gn:admin1_code":"GF",
    "gn:admin2_code":"973",
    "gn:admin3_code":"9731",
    "gn:admin4_code":"97358",
    "gn:asciiname":"Embouchure",
    "gn:country_code":"GF",
    "gn:dem":33,
    "gn:feature_class":"P",
    "gn:feature_code":"PPL",
    "gn:name":"Embouchure",
    "gn:population":0,
    "gn:timezone":"America/Cayenne",
    "iso:country":"GF",
    "name:cat_x_preferred":[
        "Embocadura"
    ],
    "name:deu_x_preferred":[
        "Ansatz"
    ],
    "name:epo_x_preferred":[
        "Bu\u015dteno"
    ],
    "name:fin_x_preferred":[
        "Ansatsi"
    ],
    "name:fra_x_preferred":[
        "Embouchure"
    ],
    "name:heb_x_preferred":[
        "\u05d0\u05de\u05d1\u05d5\u05e9\u05d9\u05d5\u05e8"
    ],
    "name:jpn_x_preferred":[
        "\u30a2\u30f3\u30d6\u30b7\u30e5\u30a2"
    ],
    "name:nld_x_preferred":[
        "Embouchure"
    ],
    "name:nor_x_preferred":[
        "Embouchure"
    ],
    "name:por_x_preferred":[
        "Embocadura"
    ],
    "name:rus_x_preferred":[
        "\u0410\u043c\u0431\u0443\u0448\u044e\u0440"
    ],
    "name:spa_x_preferred":[
        "Embocadura"
    ],
    "name:srp_x_preferred":[
        "\u0410\u043c\u0431\u0430\u0436\u0443\u0440\u0430"
    ],
    "name:swe_x_preferred":[
        "Embouchure"
    ],
    "name:ukr_x_preferred":[
        "\u0410\u043c\u0431\u0443\u0448\u0443\u0440"
    ],
    "wof:name":"Embouchure",
    "wof:placetype":"locality"
},
  "geometry": {"coordinates":[-53.03229,4.974],"type":"Point"}
}