{
  "type": "Feature",
  "properties": {
    "gn:admin1_code":"GF",
    "gn:admin2_code":"973",
    "gn:admin3_code":"9731",
    "gn:admin4_code":"97313",
    "gn:asciiname":"Crique Anguille",
    "gn:country_code":"GF",
    "gn:dem":21,
    "gn:feature_class":"P",
    "gn:feature_code":"PPL",
    "gn:name":"Crique Anguille",
    "gn:population":0,
    "gn:timezone":"America/Cayenne",
    "iso:country":"GF",
    "wof:name":"Crique Anguille",
    "wof:placetype":"locality"
},
  "geometry": {"coordinates":[-52.50966,4.83265],"type":"Point"}
}