{
  "type": "Feature",
  "properties": {
    "gn:admin1_code":"GF",
    "gn:admin2_code":"973",
    "gn:admin3_code":"9732",
    "gn:admin4_code":"97311",
    "gn:asciiname":"Esperance",
    "gn:country_code":"GF",
    "gn:dem":11,
    "gn:feature_class":"P",
    "gn:feature_code":"PPL",
    "gn:name":"Esp\u00e9rance",
    "gn:population":0,
    "gn:timezone":"America/Cayenne",
    "iso:country":"GF",
    "name:fra_x_preferred":[
        "Esp\u00e9rance"
    ],
    "wof:name":"Esperance",
    "wof:placetype":"locality"
},
  "geometry": {"coordinates":[-54.052,5.43346],"type":"Point"}
}