{
  "type": "Feature",
  "properties": {
    "gn:admin1_code":"GF",
    "gn:admin2_code":"973",
    "gn:admin3_code":"9732",
    "gn:admin4_code":"97311",
    "gn:asciiname":"Esperance",
    "gn:country_code":"GF",
    "gn:dem":11,
    "gn:feature_class":"P",
    "gn:feature_code":"PPL",
    "gn:name":"Esp\u00e9rance",
    "gn:population":0,
    "gn:timezone":"America/Cayenne",
    "iso:country":"GF",
    "name:ben_x_preferred":[
        "\u098f\u09b8\u09cd\u09aa\u09c7\u09b0\u09be\u09a8\u09cd\u09b8"
    ],
    "name:cat_x_preferred":[
        "Esperance"
    ],
    "name:ceb_x_preferred":[
        "Esperance"
    ],
    "name:ell_x_preferred":[
        "\u0388\u03c3\u03c0\u03b5\u03c1\u03b1\u03bd\u03c2"
    ],
    "name:est_x_preferred":[
        "Esperance"
    ],
    "name:fra_x_preferred":[
        "Esp\u00e9rance"
    ],
    "name:heb_x_preferred":[
        "\u05d0\u05e1\u05e4\u05e8\u05e0\u05e1"
    ],
    "name:hun_x_preferred":[
        "Esperance"
    ],
    "name:ind_x_preferred":[
        "Esperance"
    ],
    "name:ita_x_preferred":[
        "Esperance"
    ],
    "name:nld_x_preferred":[
        "Esperance"
    ],
    "name:pol_x_preferred":[
        "Esperance"
    ],
    "name:por_x_preferred":[
        "Esperance"
    ],
    "name:rus_x_preferred":[
        "\u042d\u0441\u043f\u0435\u0440\u0430\u043d\u0441"
    ],
    "name:spa_x_preferred":[
        "Esperance"
    ],
    "name:srp_x_preferred":[
        "\u0415\u0441\u043f\u0435\u0440\u0430\u043d\u0441"
    ],
    "name:swe_x_preferred":[
        "Esperance"
    ],
    "name:tur_x_preferred":[
        "Esperance"
    ],
    "name:ukr_x_preferred":[
        "\u0415\u0441\u043f\u0435\u0440\u0430\u043d\u0441"
    ],
    "name:urd_x_preferred":[
        "\u0627\u06cc\u0633\u067e\u06cc\u0631\u0627\u0646\u0633\u06d2"
    ],
    "name:vie_x_preferred":[
        "Esperance"
    ],
    "name:vol_x_preferred":[
        "Esperance"
    ],
    "wof:name":"Esperance",
    "wof:placetype":"locality"
},
  "geometry": {"coordinates":[-54.052,5.43346],"type":"Point"}
}