{
  "type": "Feature",
  "properties": {
    "gn:admin1_code":"GF",
    "gn:admin2_code":"973",
    "gn:admin3_code":"9731",
    "gn:admin4_code":"97309",
    "gn:asciiname":"Montravel",
    "gn:country_code":"GF",
    "gn:dem":11,
    "gn:feature_class":"P",
    "gn:feature_code":"PPL",
    "gn:name":"Montravel",
    "gn:population":0,
    "gn:timezone":"America/Cayenne",
    "iso:country":"GF",
    "name:ceb_x_preferred":[
        "Montravel"
    ],
    "name:deu_x_preferred":[
        "Montravel"
    ],
    "name:fra_x_preferred":[
        "Montravel"
    ],
    "name:swe_x_preferred":[
        "Montravel"
    ],
    "wof:name":"Montravel",
    "wof:placetype":"locality"
},
  "geometry": {"coordinates":[-52.26508,4.9047],"type":"Point"}
}