{
  "type": "Feature",
  "properties": {
    "gn:admin1_code":"GF",
    "gn:admin2_code":"973",
    "gn:admin3_code":"9731",
    "gn:admin4_code":"97356",
    "gn:asciiname":"Degrad Saint-Pierre",
    "gn:country_code":"GF",
    "gn:dem":85,
    "gn:feature_class":"P",
    "gn:feature_code":"PPL",
    "gn:name":"D\u00e9grad Saint-Pierre",
    "gn:population":0,
    "gn:timezone":"America/Cayenne",
    "iso:country":"GF",
    "wof:name":"Degrad Saint-Pierre",
    "wof:placetype":"locality"
},
  "geometry": {"coordinates":[-52.65,3.11667],"type":"Point"}
}