{
  "type": "Feature",
  "properties": {
    "gn:admin1_code":"GF",
    "gn:admin2_code":"973",
    "gn:admin3_code":"9732",
    "gn:admin4_code":"97353",
    "gn:asciiname":"Adala",
    "gn:country_code":"GF",
    "gn:dem":96,
    "gn:feature_class":"P",
    "gn:feature_code":"PPL",
    "gn:name":"Adala",
    "gn:population":0,
    "gn:timezone":"America/Paramaribo",
    "iso:country":"GF",
    "name:fra_x_preferred":[
        "Adala"
    ],
    "wof:name":"Adala",
    "wof:placetype":"locality"
},
  "geometry": {"coordinates":[-54.04846,3.63552],"type":"Point"}
}