{
  "type": "Feature",
  "properties": {
    "gn:admin1_code":"GF",
    "gn:admin2_code":"973",
    "gn:admin3_code":"9731",
    "gn:admin4_code":"97309",
    "gn:asciiname":"Beau Soleil",
    "gn:country_code":"GF",
    "gn:dem":4,
    "gn:feature_class":"P",
    "gn:feature_code":"PPL",
    "gn:name":"Beau Soleil",
    "gn:population":0,
    "gn:timezone":"America/Cayenne",
    "iso:country":"GF",
    "name:fra_x_preferred":[
        "Beau Soleil"
    ],
    "wof:name":"Beau Soleil",
    "wof:placetype":"locality"
},
  "geometry": {"coordinates":[-52.25399,4.86391],"type":"Point"}
}