{
  "type": "Feature",
  "properties": {
    "gn:admin1_code":"GF",
    "gn:admin2_code":"973",
    "gn:admin3_code":"9731",
    "gn:admin4_code":"97356",
    "gn:asciiname":"Itousanseng",
    "gn:country_code":"GF",
    "gn:dem":159,
    "gn:feature_class":"P",
    "gn:feature_code":"PPL",
    "gn:name":"Itousanseng",
    "gn:population":0,
    "gn:timezone":"America/Cayenne",
    "iso:country":"GF",
    "name:und_x_variant":[
        "Villages Oyampi",
        "Itousanseng"
    ],
    "wof:name":"Itousanseng",
    "wof:placetype":"locality"
},
  "geometry": {"coordinates":[-52.91891,2.19635],"type":"Point"}
}