{
  "type": "Feature",
  "properties": {
    "gn:admin1_code":"GF",
    "gn:admin2_code":"973",
    "gn:admin3_code":"9731",
    "gn:admin4_code":"97308",
    "gn:asciiname":"Labombe",
    "gn:country_code":"GF",
    "gn:dem":25,
    "gn:feature_class":"P",
    "gn:feature_code":"PPL",
    "gn:name":"Labombe",
    "gn:population":0,
    "gn:timezone":"America/Cayenne",
    "iso:country":"GF",
    "name:fra_x_preferred":[
        "Labombe"
    ],
    "wof:name":"Labombe",
    "wof:placetype":"locality"
},
  "geometry": {"coordinates":[-51.82033,3.92875],"type":"Point"}
}