{
  "type": "Feature",
  "properties": {
    "gn:admin1_code":"GF",
    "gn:admin2_code":"973",
    "gn:admin3_code":"9732",
    "gn:admin4_code":"97360",
    "gn:asciiname":"Sissilia",
    "gn:country_code":"GF",
    "gn:dem":22,
    "gn:feature_class":"P",
    "gn:feature_code":"PPL",
    "gn:name":"Sissilia",
    "gn:population":0,
    "gn:timezone":"America/Cayenne",
    "iso:country":"GF",
    "name:fra_x_preferred":[
        "Sissilia"
    ],
    "wof:name":"Sissilia",
    "wof:placetype":"locality"
},
  "geometry": {"coordinates":[-54.43903,4.98102],"type":"Point"}
}